django_aux/__init__.py
django_aux/admin.py
django_aux/apps.py
django_aux/columns.py
django_aux/decorators.py
django_aux/factory.py
django_aux/filters.py
django_aux/forms.py
django_aux/middleware.py
django_aux/models.py
django_aux/urls.py
django_aux/utils.py
django_aux/views.py
django_aux/migrations/__init__.py
django_aux/static/css/main.css
django_aux/static/js/save_set_collapse_status.js
django_aux/static/js/save_set_scroll_pos.js
django_aux/static/js/show_hide_remove_btn.js
django_aux/templates/django_aux/base.html
django_aux/templates/django_aux/checkbox-table.html
django_aux/templates/django_aux/dash-filter.html
django_aux/templates/django_aux/delete.html
django_aux/templates/django_aux/form-table.html
django_aux/templates/django_aux/inline-formset.html
django_aux/templates/django_aux/login.html
django_aux/templates/django_aux/logout.html
django_aux/templates/django_aux/standard-plotly.html
django_aux/templates/django_aux/standard.html
django_aux/templatetags/__init__.py
django_aux/templatetags/aux_tags.py
django_aux-0.0.96.dist-info/licenses/LICENSE
django_aux_geo/__init__.py
django_aux_geo/apps.py
django_aux_geo/filters.py
django_aux_geo/models.py
django_aux_geo/tables.py
django_aux_geo/migrations/0001_initial.py
django_aux_geo/migrations/0002_address_coordinate_coordinate_unique_coord_and_more.py
django_aux_geo/migrations/__init__.py
django_aux_request/__init__.py
django_aux_request/apps.py
django_aux_request/filters.py
django_aux_request/tables.py
django_aux_request/urls.py
django_aux_request/views.py
django_aux_timeperiods/__init__.py
django_aux_timeperiods/admin.py
django_aux_timeperiods/apps.py
django_aux_timeperiods/models.py
django_aux_timeperiods/migrations/0001_initial.py
django_aux_timeperiods/migrations/0002_alter_day_options_alter_month_options_and_more.py
django_aux_timeperiods/migrations/__init__.py
tests/__init__.py
tests/filters.py
tests/forms.py
tests/models.py
tests/tables.py
tests/test_daux.py
tests/test_daux_geo.py
tests/test_daux_timeperiods.py
tests/test_settings.py
tests/urls.py
django_aux-0.0.96.dist-info/METADATA
django_aux-0.0.96.dist-info/WHEEL
django_aux-0.0.96.dist-info/top_level.txt
django_aux-0.0.96.dist-info/RECORD
